CHRLINE/__init__.py
CHRLINE/api.py
CHRLINE/client.py
CHRLINE/config.py
CHRLINE/cube.py
CHRLINE/e2ee.py
CHRLINE/exceptions.py
CHRLINE/helpers.py
CHRLINE/hooks.py
CHRLINE/models.py
CHRLINE/object.py
CHRLINE/poll.py
CHRLINE/server.py
CHRLINE/thrift.py
CHRLINE/timeline.py
CHRLINE/timelineBiz.py
CHRLINE/BIZ/__init__.py
CHRLINE/BIZ/TL/ST.py
CHRLINE/BIZ/TL/__init__.py
CHRLINE/dyher/__init__.py
CHRLINE/dyher/conn.py
CHRLINE/dyher/connManager.py
CHRLINE/hksc/__init__.py
CHRLINE/hksc/database.py
CHRLINE/hksc/events.py
CHRLINE/hksc/types.py
CHRLINE/hksc/utility.py
CHRLINE/serializers/DummyProtocol.py
CHRLINE/serializers/__init__.py
CHRLINE/services/AccessTokenRefreshService.py
CHRLINE/services/AccountAuthFactorEapConnectService.py
CHRLINE/services/AuthService.py
CHRLINE/services/BaseService.py
CHRLINE/services/BotExternalService.py
CHRLINE/services/BuddyService.py
CHRLINE/services/CallService.py
CHRLINE/services/ChannelService.py
CHRLINE/services/ChatAppService.py
CHRLINE/services/E2EEKeyBackupService.py
CHRLINE/services/HomeSafetyCheckService.py
CHRLINE/services/InterlockService.py
CHRLINE/services/LiffService.py
CHRLINE/services/LoginService.py
CHRLINE/services/OaMembershipService.py
CHRLINE/services/PrimaryAccountInitService.py
CHRLINE/services/PrimaryQrCodeMigrationLongPollingService.py
CHRLINE/services/PrimaryQrCodeMigrationPreparationService.py
CHRLINE/services/PwlessPrimaryRegistrationService.py
CHRLINE/services/RelationService.py
CHRLINE/services/SearchService.py
CHRLINE/services/SecondaryPwlessLoginPermitNoticeService.py
CHRLINE/services/SecondaryPwlessLoginService.py
CHRLINE/services/SettingsService.py
CHRLINE/services/ShopAuthService.py
CHRLINE/services/ShopService.py
CHRLINE/services/SquareBotService.py
CHRLINE/services/SquareLiveTalkService.py
CHRLINE/services/SquareService.py
CHRLINE/services/TalkService.py
CHRLINE/services/TestService.py
CHRLINE/services/__init__.py
CHRLINE/services/thrift/AccessTokenRefreshService.py
CHRLINE/services/thrift/BuddyService.py
CHRLINE-2.5.14.dist-info/LICENSE
CHRLINE-2.5.14.dist-info/METADATA
CHRLINE-2.5.14.dist-info/WHEEL
CHRLINE-2.5.14.dist-info/top_level.txt
CHRLINE-2.5.14.dist-info/RECORD
